my_tiny_library/__init__.py
my_tiny_library-0.1.dist-info/METADATA
my_tiny_library-0.1.dist-info/WHEEL
my_tiny_library-0.1.dist-info/top_level.txt
my_tiny_library-0.1.dist-info/RECORD
