Metadata-Version: 2.1
Name: my-tiny-library
Version: 0.1
Summary: A tiny Python library to greet users.
Home-page: https://github.com/yourusername/my_tiny_library
Author: Tarik Kasbaoui
Author-email: your.email@example.com
License: MIT
Platform: UNKNOWN
